CHANGELOG.txt
LICENSE.txt
MANIFEST.in
README.txt
setup.py
EDALIB/__init__.py
buildlytics.egg-info/PKG-INFO
buildlytics.egg-info/SOURCES.txt
buildlytics.egg-info/dependency_links.txt
buildlytics.egg-info/requires.txt
buildlytics.egg-info/top_level.txt