Metadata-Version: 1.1
Name: buildlytics
Version: 0.0.3
Summary: A comprehensive way to make your Exploratory data analysis process easy by using our package
Home-page: UNKNOWN
Author: UNKNOWN
Author-email: UNKNOWN
License: MIT
Platform: any
Classifier: Programming Language :: Python
Classifier: Operating System :: OS Independent
Classifier: Intended Audience :: Science/Research
Classifier: Topic :: Scientific/Engineering
